{
  "db_name": "SQLite",
  "query": "SELECT origin, topic, source, data FROM finalized_events WHERE block_height = ?",
  "describe": {
    "columns": [
      {
        "name": "origin",
        "ordinal": 0,
        "type_info": "Text"
      },
      {
        "name": "topic",
        "ordinal": 1,
        "type_info": "Text"
      },
      {
        "name": "source",
        "ordinal": 2,
        "type_info": "Text"
      },
      {
        "name": "data",
        "ordinal": 3,
        "type_info": "Blob"
      }
    ],
    "parameters": {
      "Right": 1
    },
    "nullable": [
      false,
      false,
      false,
      false
    ]
  },
  "hash": "4c90fe749d3dbd3f04844450d966f88395b35949d9a213891f7eb1b0ccbc2fff"
}
